pysagem/__init__.py
pysagem/animation.py
pysagem/cli.py
pysagem/events.py
pysagem/main.py
pysagem/plotstyle.mplstyle
pysagem/utils.py
pysagem-1.0.1.dist-info/LICENSE
pysagem-1.0.1.dist-info/METADATA
pysagem-1.0.1.dist-info/WHEEL
pysagem-1.0.1.dist-info/entry_points.txt
pysagem-1.0.1.dist-info/top_level.txt
pysagem-1.0.1.dist-info/RECORD
